dataShare/__init__.py
dataShare/main.py
easyDataShare-1.1.dist-info/METADATA
easyDataShare-1.1.dist-info/WHEEL
easyDataShare-1.1.dist-info/top_level.txt
easyDataShare-1.1.dist-info/RECORD
