Metadata-Version: 2.2
Name: easyDataShare
Version: 1.1
Summary: Easiest dataSharing library
Dynamic: summary
